README.rst
setup.py
google_play/__init__.py
google_play.egg-info/PKG-INFO
google_play.egg-info/SOURCES.txt
google_play.egg-info/dependency_links.txt
google_play.egg-info/requires.txt
google_play.egg-info/top_level.txt