Metadata-Version: 1.0
Name: google-play
Version: 0.2.1
Summary: Google Play app fetcher
Home-page: https://github.com/h2rd/google_play
Author: Igor Skrynkovskyy
Author-email: skrynkovskyy@gmail.com
License: MIT
Platform: UNKNOWN
